ds.py
setup.py
ds.egg-info/PKG-INFO
ds.egg-info/SOURCES.txt
ds.egg-info/dependency_links.txt
ds.egg-info/entry_points.txt
ds.egg-info/top_level.txt