Metadata-Version: 1.1
Name: ds
Version: 0.0.1
Summary: Simple data query language
Home-page: https://github.com/asciimoo/ds
Author: Adam Tauber
Author-email: asciimoo@gmail.com
License: AGPLv3+
Download-URL: https://github.com/asciimoo/ds/tarball/master
Keywords: data query
Platform: UNKNOWN
Classifier: Development Status :: 4 - Beta
Classifier: Topic :: Utilities
Classifier: Environment :: Console
Classifier: License :: OSI Approved :: GNU Affero General Public License v3
